{
	"info": {
		"_postman_id": "fe134770-74bf-411b-b437-30b8b0923969",
		"name": "API Task 8",
		"schema": "https://schema.getpostman.com/json/collection/v2.1.0/collection.json",
		"_exporter_id": "18622517"
	},
	"item": [
		{
			"name": "Get Status",
			"event": [
				{
					"listen": "test",
					"script": {
						"exec": [
							"postman.setNextRequest(\"Place a book order\")"
						],
						"type": "text/javascript"
					}
				}
			],
			"request": {
				"method": "GET",
				"header": [],
				"url": {
					"raw": "https://simple-books-api.glitch.me/",
					"protocol": "https",
					"host": [
						"simple-books-api",
						"glitch",
						"me"
					],
					"path": [
						""
					]
				}
			},
			"response": []
		},
		{
			"name": "Register an API Client",
			"event": [
				{
					"listen": "test",
					"script": {
						"exec": [
							""
						],
						"type": "text/javascript"
					}
				}
			],
			"request": {
				"auth": {
					"type": "bearer",
					"bearer": [
						{
							"key": "token",
							"value": "d6b1063208495fab5930d94e912152ee3eb65cc0f5b7eb6fd98a09f0c091fe73",
							"type": "string"
						}
					]
				},
				"method": "POST",
				"header": [],
				"body": {
					"mode": "raw",
					"raw": "{\r\n   \"clientName\": \"Johny\",\r\n   \"clientEmail\": \"aridun@gmail.com\"\r\n}",
					"options": {
						"raw": {
							"language": "json"
						}
					}
				},
				"url": {
					"raw": "https://simple-books-api.glitch.me/api-clients/",
					"protocol": "https",
					"host": [
						"simple-books-api",
						"glitch",
						"me"
					],
					"path": [
						"api-clients",
						""
					]
				}
			},
			"response": []
		},
		{
			"name": "Get Books",
			"event": [
				{
					"listen": "test",
					"script": {
						"exec": [
							"pm.test(\"Status code is 200\", function () {\r",
							"    pm.response.to.have.status(200);\r",
							"    \r",
							"});\r",
							"    const jsonData = pm.response.json();\r",
							"    const theRussianBook = jsonData.find(({ name }) => name === \"The Russian\");\r",
							"    console.log(theRussianBook);\r",
							"\r",
							"pm.environment.set(\"russian_id\", theRussianBook.id);\r",
							""
						],
						"type": "text/javascript"
					}
				}
			],
			"request": {
				"auth": {
					"type": "bearer",
					"bearer": [
						{
							"key": "token",
							"value": "d6b1063208495fab5930d94e912152ee3eb65cc0f5b7eb6fd98a09f0c091fe73",
							"type": "string"
						}
					]
				},
				"method": "GET",
				"header": [],
				"url": {
					"raw": "https://simple-books-api.glitch.me/books",
					"protocol": "https",
					"host": [
						"simple-books-api",
						"glitch",
						"me"
					],
					"path": [
						"books"
					],
					"query": [
						{
							"key": "type",
							"value": "non-fiction",
							"disabled": true
						}
					]
				}
			},
			"response": []
		},
		{
			"name": "Get a single book",
			"protocolProfileBehavior": {
				"disableBodyPruning": true
			},
			"request": {
				"method": "GET",
				"header": [],
				"body": {
					"mode": "raw",
					"raw": "",
					"options": {
						"raw": {
							"language": "json"
						}
					}
				},
				"url": {
					"raw": "https://simple-books-api.glitch.me/books/:bookId",
					"protocol": "https",
					"host": [
						"simple-books-api",
						"glitch",
						"me"
					],
					"path": [
						"books",
						":bookId"
					],
					"query": [
						{
							"key": "",
							"value": "",
							"disabled": true
						}
					],
					"variable": [
						{
							"key": "bookId",
							"value": "6"
						}
					]
				}
			},
			"response": []
		},
		{
			"name": "Place a book order",
			"event": [
				{
					"listen": "test",
					"script": {
						"exec": [
							"// postman.setNextRequest(\"Get all orders\")"
						],
						"type": "text/javascript"
					}
				}
			],
			"request": {
				"auth": {
					"type": "bearer",
					"bearer": [
						{
							"key": "token",
							"value": "d6b1063208495fab5930d94e912152ee3eb65cc0f5b7eb6fd98a09f0c091fe73",
							"type": "string"
						}
					]
				},
				"method": "POST",
				"header": [
					{
						"key": "Token",
						"value": "03c5abfe090876ab74a2a2ac4c079174a35fd88c9b88cd2164ff4b9d56c31d6c",
						"type": "text"
					}
				],
				"body": {
					"mode": "raw",
					"raw": "{\r\n  \"bookId\": 1,\r\n  \"customerName\": \"Jane\"\r\n}",
					"options": {
						"raw": {
							"language": "json"
						}
					}
				},
				"url": {
					"raw": "https://simple-books-api.glitch.me/orders",
					"protocol": "https",
					"host": [
						"simple-books-api",
						"glitch",
						"me"
					],
					"path": [
						"orders"
					]
				}
			},
			"response": []
		},
		{
			"name": "Get all orders",
			"event": [
				{
					"listen": "test",
					"script": {
						"exec": [
							""
						],
						"type": "text/javascript"
					}
				}
			],
			"protocolProfileBehavior": {
				"disableBodyPruning": true
			},
			"request": {
				"auth": {
					"type": "bearer",
					"bearer": [
						{
							"key": "token",
							"value": "d6b1063208495fab5930d94e912152ee3eb65cc0f5b7eb6fd98a09f0c091fe73",
							"type": "string"
						}
					]
				},
				"method": "GET",
				"header": [],
				"body": {
					"mode": "raw",
					"raw": "",
					"options": {
						"raw": {
							"language": "json"
						}
					}
				},
				"url": {
					"raw": "https://simple-books-api.glitch.me/orders",
					"protocol": "https",
					"host": [
						"simple-books-api",
						"glitch",
						"me"
					],
					"path": [
						"orders"
					]
				}
			},
			"response": []
		},
		{
			"name": "Get an order",
			"protocolProfileBehavior": {
				"disableBodyPruning": true
			},
			"request": {
				"auth": {
					"type": "bearer",
					"bearer": [
						{
							"key": "token",
							"value": "d6b1063208495fab5930d94e912152ee3eb65cc0f5b7eb6fd98a09f0c091fe73",
							"type": "string"
						}
					]
				},
				"method": "GET",
				"header": [],
				"body": {
					"mode": "raw",
					"raw": "",
					"options": {
						"raw": {
							"language": "json"
						}
					}
				},
				"url": {
					"raw": "https://simple-books-api.glitch.me/orders/:orderId",
					"protocol": "https",
					"host": [
						"simple-books-api",
						"glitch",
						"me"
					],
					"path": [
						"orders",
						":orderId"
					],
					"variable": [
						{
							"key": "orderId",
							"value": "Zoz_uHQNYVgqaaD5qwcZe"
						}
					]
				}
			},
			"response": []
		},
		{
			"name": "Delete an order",
			"event": [
				{
					"listen": "test",
					"script": {
						"exec": [
							""
						],
						"type": "text/javascript"
					}
				}
			],
			"request": {
				"auth": {
					"type": "bearer",
					"bearer": [
						{
							"key": "token",
							"value": "d6b1063208495fab5930d94e912152ee3eb65cc0f5b7eb6fd98a09f0c091fe73",
							"type": "string"
						}
					]
				},
				"method": "DELETE",
				"header": [],
				"body": {
					"mode": "raw",
					"raw": "",
					"options": {
						"raw": {
							"language": "json"
						}
					}
				},
				"url": {
					"raw": "https://simple-books-api.glitch.me/orders/:orderId",
					"protocol": "https",
					"host": [
						"simple-books-api",
						"glitch",
						"me"
					],
					"path": [
						"orders",
						":orderId"
					],
					"variable": [
						{
							"key": "orderId",
							"value": "Zoz_uHQNYVgqaaD5qwcZe"
						}
					]
				}
			},
			"response": []
		},
		{
			"name": "Book Untamed",
			"event": [
				{
					"listen": "test",
					"script": {
						"exec": [
							"const jsonData = pm.response.json();\r",
							"\r",
							"const untamed = jsonData.find(book => book.name === \"Untamed\");;\r",
							"\r",
							" pm.test(\"verify the id number of a non-fiction book with the name Untamed\", function() {\r",
							"        pm.expect(untamed.id).to.equal(5);\r",
							"    });\r",
							"\r",
							"    console.log(\"ID for 'Untamed':\", untamed.id);"
						],
						"type": "text/javascript"
					}
				}
			],
			"request": {
				"auth": {
					"type": "bearer",
					"bearer": [
						{
							"key": "token",
							"value": "d6b1063208495fab5930d94e912152ee3eb65cc0f5b7eb6fd98a09f0c091fe73",
							"type": "string"
						}
					]
				},
				"method": "GET",
				"header": [],
				"url": {
					"raw": "https://simple-books-api.glitch.me/books",
					"protocol": "https",
					"host": [
						"simple-books-api",
						"glitch",
						"me"
					],
					"path": [
						"books"
					]
				}
			},
			"response": []
		}
	]
}